sj_tool/__init__.py
sj_tool/decorator.py
sj_tool/email.py
sj_tool/file.py
sj_tool/http_util.py
sj_tool/json.py
sj_tool/json_util.py
sj_tool/language.py
sj_tool/parallel.py
sj_tool/parallel_util.py
sj_tool/scheduler.py
sj_tool/system.py
sj_tool/util.py
sj_tool/db/__init__.py
sj_tool/db/mongo.py
sj_tool/db/mongo_util.py
sj_tool/db/mysql.py
sj_tool/db/sql_util.py
sj_tool/fjsp/__init__.py
sj_tool/fjsp/builder.py
sj_tool/fjsp/check.py
sj_tool/fjsp/result_generator.py
sj_tool/fjsp/time_util.py
sj_tool/fjsp/entity/__init__.py
sj_tool/fjsp/entity/changeover.py
sj_tool/fjsp/entity/fjsp_pool.py
sj_tool/fjsp/entity/job.py
sj_tool/fjsp/entity/machine.py
sj_tool/fjsp/entity/operation.py
sj_tool/fjsp/entity/order.py
sj_tool/fjsp/entity/process.py
sj_tool/fjsp/entity/product.py
sj_tool/fjsp/entity/standing_time.py
sj_tool/fjsp/erp_next/__init__.py
sj_tool/fjsp/erp_next/constant.py
sj_tool/fjsp/erp_next/data_sync.py
sj_tool/fjsp/erp_next/data_write_back.py
sj_tool/fjsp/erp_next/util.py
sj_tool/logger/__init__.py
sj_tool/logger/logger.py
sj_tool/logger/text_logger.py
sj_tool/logger/visual_logger.py
sj_tool-1.0.89.dist-info/METADATA
sj_tool-1.0.89.dist-info/WHEEL
sj_tool-1.0.89.dist-info/top_level.txt
sj_tool-1.0.89.dist-info/RECORD
