Metadata-Version: 2.1
Name: sj-tool
Version: 1.0.89
Summary: 工具库
Home-page: 
Author: Weixian Shi
Author-email: shiweixian@entroduction.cn
Requires-Dist: numpy
Requires-Dist: pytest-shutil
Requires-Dist: peewee
Requires-Dist: pymysql
Requires-Dist: pymongo
Requires-Dist: pandas
Requires-Dist: loguru
Requires-Dist: visualdl
Requires-Dist: tensorboardX
Requires-Dist: apscheduler
Requires-Dist: yagmail
Requires-Dist: build
Requires-Dist: twine
Requires-Dist: deprecated
